miscelaneos/Byte_Striping/bpbs.v
//Tarea 6 Alejandro Rojas Cordero B36049
`include "byte_striping.v"
module bpbs ( output reg clk, reset, valid,
   output reg [7:0] data,
   output reg [7:0] data_out0, data_out1, data_out2, data_out3);

   initial
     begin	
	reset=0;
	clk=0;
	valid=0;
	data <= 8'b00000000;
	data_out0 <= 8'b00000000;
	data_out1 <= 8'b00000000;
	data_out2 <= 8'b00000000;
	data_out3 <= 8'b00000000;
	#15 valid=1;
	#30 reset=1;
	#20 data <= 8'b00000001;
	#20 data <= 8'b00000010;
	#20 data <= 8'b00000100;
	#20 data <= 8'b00001000;
	#20 data <= 8'b00010000;
	#20 data <= 8'b00100000;

     end

   always
     begin
	#5 clk = ~clk;	
	
     end

endmodule

miscelaneos/Byte_Striping/byte_striping.v
//Proyecto #1 Circuitos Digitales 2//
module bytestripingRX( input clk, reset, valid,
   input [7:0] data,
   output reg [7:0] data_out0, data_out1, data_out2, data_out3);

  reg [7:0] data_out0_next, data_out1_next, data_out2_next, data_out3_next;

//Indice de registro de los 4 estados,
 parameter [4:0] LaneA = 1,
		 LaneB = 2,
		 LaneC = 3,
		 LaneD = 4,
		 Estado0 =5; //Me da la señal para empezar
		
 reg [7:0] state, next_state; // Se le asignan 8 bits para utlizar one-hot.

//Bloque de Flip Flops
 always @(posedge clk or negedge reset)

	if(!reset)begin
	  state[LaneA] <= 1'b1;
	  data_out0<=8'b00000000;
	  data_out1<=8'b00000000;
	  data_out2<=8'b00000000;
	  data_out3<=8'b00000000;
	end
	else begin state <= next_state;
		data_out0<=data_out0_next;
		data_out1<=data_out1_next;	//Flops para mantener el dato y evitar latches
		data_out2<=data_out2_next;
		data_out3<=data_out3_next;
	end
		

// Bloque de asignacion de los estados y sus transiciones.
 always@(*) begin
	next_state = 8'b00000000;
	data_out0_next=data_out0;  //Evita los Latch inferidos
	data_out1_next=data_out1;
	data_out2_next=data_out2;
	data_out3_next=data_out3;
	case (1'b1)

		state[Estado0]: if(valid) begin next_state [LaneA] = 1'b1;
				
					data_out0_next=data;

			      	end else   next_state [Estado0] = 1'b1;

	
		state[LaneA]: if(valid) begin next_state [LaneB] = 1'b1;
				
					data_out1_next=data;
				
			      end else   next_state [LaneA] = 1'b1;
		
		state[LaneB]: if(valid)begin  next_state [LaneC] = 1'b1;

					data_out2_next=data;			

			      end else   next_state [LaneB] = 1'b1;
		
		state[LaneC]: if(valid) begin next_state [LaneD] = 1'b1;

					data_out3_next=data;

			      end else next_state [LaneC] = 1'b1;
      		
		state[LaneD]: if(valid) begin next_state [LaneA] = 1'b1;

				
					data_out0_next = data;			

			      end else next_state [LaneD] = 1'b1;
	endcase
end
endmodule

miscelaneos/Byte_Striping/tbbs.v
//Alejandro Rojas Cordero Tarea 6 B36049
`include "bpbs.v"

module tbbs;

wire clk;

bytestripingRX bytestrip (.clk(clk), .data(data), .reset(reset),.valid(valid),.data_out0(data_out0), .data_out1(data_out1), .data_out2(data_out2), .data_out3(data_out3));
bpbs bancopruebasBS (.clk(clk), .data(data), .reset(reset), .valid(valid),.data_out0(data_out0), .data_out1(data_out1), .data_out2(data_out2), .data_out3(data_out3));

initial begin
    
  //-- Fichero donde almacenar los resultados
  $dumpfile("prueba_Byte_Striping.vcd");
  $dumpvars(0, tbbs);
    
  # 600 $display("FIN TestBench");
  $finish;
end


endmodule

Byte_Striping/prueba_Byte_Striping.vcd
$date
	Wed May 23 08:26:28 2018
$end
$version
	Icarus Verilog
$end
$timescale
	1s
$end
$scope module tbbs $end
$var wire 1 ! data_out0 $end
$var wire 1 " data_out1 $end
$var wire 1 # data_out2 $end
$var wire 1 $ data_out3 $end
$var wire 1 % valid $end
$var wire 1 & reset $end
$var wire 1 ' data $end
$var wire 1 ( clk $end
$scope module bancopruebasBS $end
$var reg 1 ( clk $end
$var reg 8 ) data [7:0] $end
$var reg 8 * data_out0 [7:0] $end
$var reg 8 + data_out1 [7:0] $end
$var reg 8 , data_out2 [7:0] $end
$var reg 8 - data_out3 [7:0] $end
$var reg 1 & reset $end
$var reg 1 % valid $end
$upscope $end
$scope module bytestrip $end
$var wire 1 ( clk $end
$var wire 8 . data [7:0] $end
$var wire 1 & reset $end
$var wire 1 % valid $end
$var reg 8 / data_out0 [7:0] $end
$var reg 8 0 data_out0_next [7:0] $end
$var reg 8 1 data_out1 [7:0] $end
$var reg 8 2 data_out1_next [7:0] $end
$var reg 8 3 data_out2 [7:0] $end
$var reg 8 4 data_out2_next [7:0] $end
$var reg 8 5 data_out3 [7:0] $end
$var reg 8 6 data_out3_next [7:0] $end
$var reg 8 7 next_state [7:0] $end
$var reg 8 8 state [7:0] $end
$upscope $end
$upscope $end
$enddefinitions $end
#0
$dumpvars
bx1x 8
b10 7
b0 6
b0 5
b0 4
b0 3
b0 2
b0 1
b0 0
b0 /
b0 .
b0 -
b0 ,
b0 +
b0 *
b0 )
0(
0'
0&
0%
0$
0#
0"
0!
$end
#5
1(
#10
0(
#15
b100 7
1(
1%
#20
0(
#25
1(
#30
0(
#35
1(
#40
0(
#45
b1000 7
b100 8
1(
1&
#50
0(
#55
b10000 7
b1000 8
1(
#60
0(
#65
b10 7
b10000 8
1(
#70
0(
#75
b1 2
b100 7
b1 .
1'
b10 8
b1 )
1(
#80
0(
#85
x"
b1 4
b1000 7
b1 1
b100 8
1(
#90
0(
#95
x#
b1 6
b10000 7
b1 3
b1000 8
1(
#100
0(
#105
x$
b10 7
b0 .
0'
b1 5
b10000 8
b10 )
1(
#110
0(
#115
b0 2
b100 7
b10 8
1(
#120
0(
#125
0"
b0 4
b1000 7
b0 1
b100 8
1(
#130
0(
#135
0#
b0 6
b10000 7
b0 3
b1000 8
b100 )
1(
#140
0(
#145
0$
b10 7
b0 5
b10000 8
1(
#150
0(
#155
b100 7
b10 8
1(
#160
0(
#165
b1000 7
b100 8
b1000 )
1(
#170
0(
#175
b10000 7
b1000 8
1(
#180
0(
#185
b10 7
b10000 8
1(
#190
0(
#195
b100 7
b10 8
b10000 )
1(
#200
0(
#205
b1000 7
b100 8
1(
#210
0(
#215
b10000 7
b1000 8
1(
#220
0(
#225
b10 7
b10000 8
b100000 )
1(
#230
0(
#235
b100 7
b10 8
1(
#240
0(
#245
b1000 7
b100 8
1(
#250
0(
#255
b10000 7
b1000 8
1(
#260
0(
#265
b10 7
b10000 8
1(
#270
0(
#275
b100 7
b10 8
1(
#280
0(
#285
b1000 7
b100 8
1(
#290
0(
#295
b10000 7
b1000 8
1(
#300
0(
#305
b10 7
b10000 8
1(
#310
0(
#315
b100 7
b10 8
1(
#320
0(
#325
b1000 7
b100 8
1(
#330
0(
#335
b10000 7
b1000 8
1(
#340
0(
#345
b10 7
b10000 8
1(
#350
0(
#355
b100 7
b10 8
1(
#360
0(
#365
b1000 7
b100 8
1(
#370
0(
#375
b10000 7
b1000 8
1(
#380
0(
#385
b10 7
b10000 8
1(
#390
0(
#395
b100 7
b10 8
1(
#400
0(
#405
b1000 7
b100 8
1(
#410
0(
#415
b10000 7
b1000 8
1(
#420
0(
#425
b10 7
b10000 8
1(
#430
0(
#435
b100 7
b10 8
1(
#440
0(
#445
b1000 7
b100 8
1(
#450
0(
#455
b10000 7
b1000 8
1(
#460
0(
#465
b10 7
b10000 8
1(
#470
0(
#475
b100 7
b10 8
1(
#480
0(
#485
b1000 7
b100 8
1(
#490
0(
#495
b10000 7
b1000 8
1(
#500
0(
#505
b10 7
b10000 8
1(
#510
0(
#515
b100 7
b10 8
1(
#520
0(
#525
b1000 7
b100 8
1(
#530
0(
#535
b10000 7
b1000 8
1(
#540
0(
#545
b10 7
b10000 8
1(
#550
0(
#555
b100 7
b10 8
1(
#560
0(
#565
b1000 7
b100 8
1(
#570
0(
#575
b10000 7
b1000 8
1(
#580
0(
#585
b10 7
b10000 8
1(
#590
0(
#595
b100 7
b10 8
1(
