miscelaneos/Byte_Striping/Tx/byte_stripingTx.v
//Proyecto #1 Circuitos Digitales 2//
module bytestripingTX( input clk, reset, valid,
   input [7:0] data,
   output reg [7:0] data_out0, data_out1, data_out2, data_out3);

  reg [7:0] data_out0_next, data_out1_next, data_out2_next, data_out3_next;

//Indice de registro de los 4 estados,
 parameter [4:0] LaneA = 1,
		 LaneB = 2,
		 LaneC = 3,
		 LaneD = 4,
		 Estado0 =5; //Me da la señal para empezar
		
 reg [7:0] state, next_state; // Se le asignan 8 bits para utlizar one-hot.

//Bloque de Flip Flops
 always @(posedge clk or reset)

	if(reset)begin
	  state <= 8'b00000000;
	  state[LaneA] <= 1'b1;
	  data_out0<=8'b00000000;
	  data_out1<=8'b00000000;
	  data_out2<=8'b00000000;
	  data_out3<=8'b00000000;
	end
	else begin state <= next_state;
		data_out0<=data_out0_next;
		data_out1<=data_out1_next;	//Flops para mantener el dato y evitar latches
		data_out2<=data_out2_next;
		data_out3<=data_out3_next;
	end
		

// Bloque de asignacion de los estados y sus transiciones.
 always@(*) begin
	next_state = 8'b00000000;
	data_out0_next=data_out0;  //Evita los Latch inferidos
	data_out1_next=data_out1;
	data_out2_next=data_out2;
	data_out3_next=data_out3;
	case (1'b1)

		state[Estado0]: if(valid) begin next_state [LaneA] = 1'b1;
				
					data_out0_next=data;

			      	end else   next_state [Estado0] = 1'b1;

	
		state[LaneA]: if(valid) begin next_state [LaneB] = 1'b1;
				
					data_out1_next=data;
				
			      end else   next_state [LaneA] = 1'b1;
		
		state[LaneB]: if(valid)begin  next_state [LaneC] = 1'b1;

					data_out2_next=data;			

			      end else   next_state [LaneB] = 1'b1;
		
		state[LaneC]: if(valid) begin next_state [LaneD] = 1'b1;

					data_out3_next=data;

			      end else next_state [LaneC] = 1'b1;
      		
		state[LaneD]: if(valid) begin next_state [LaneA] = 1'b1;

				
					data_out0_next = data;			

			      end else next_state [LaneD] = 1'b1;
	endcase
end
endmodule

miscelaneos/Byte_Striping/Tx/bpbs.v
`include "byte_stripingTx.v"
module bpbs ( output reg clk, reset, valid,
   output reg [7:0] data,
   input [7:0] data_out0, data_out1, data_out2, data_out3);

   initial
     begin	
	reset=0;
	clk=0;
	valid=0;
	data <= 8'h00;
	/*data_out0 <= 8'b00000000;
	data_out1 <= 8'b00000000;
	data_out2 <= 8'b00000000;
	data_out3 <= 8'b00000000;*/
	@(posedge clk);
	reset <=1;
	@(posedge clk);
	valid<=1;
	#10;
	@(posedge clk);
	reset <=1;
	@(posedge clk);
	valid<=1;
	@(posedge clk);
	data <= 8'h01;
	@(posedge clk);
	data <= 8'h02;
	@(posedge clk);
	data <=8'h03;
	@(posedge clk);
	data <= 8'h04;
	@(posedge clk);
	data <= 8'h05;
	@(posedge clk);
	data <= 8'h06;
	@(posedge clk);
	data <= 8'h07;
	@(posedge clk);
	data <= 8'h08;
	@(posedge clk);
	data <= 8'h09;
	@(posedge clk);
	data <= 8'h10;
	@(posedge clk);
	data <= 8'h11;
	@(posedge clk);
	data <= 8'h12;

     end

   always
     begin
	#5 clk = ~clk;	
	
     end

endmodule

miscelaneos/Byte_Striping/byte_striping.v
//Proyecto #1 Circuitos Digitales 2//
module bytestripingRX( input clk, reset, valid,
   input [7:0] data,
   output reg [7:0] data_out0, data_out1, data_out2, data_out3);

  reg [7:0] data_out0_next, data_out1_next, data_out2_next, data_out3_next;

//Indice de registro de los 4 estados,
 parameter [4:0] LaneA = 1,
		 LaneB = 2,
		 LaneC = 3,
		 LaneD = 4,
		 Estado0 =5; //Me da la señal para empezar
		
 reg [7:0] state, next_state; // Se le asignan 8 bits para utlizar one-hot.

//Bloque de Flip Flops
 always @(posedge clk or negedge reset)

	if(!reset)begin
	  state[LaneA] <= 1'b1;
	  data_out0<=8'b00000000;
	  data_out1<=8'b00000000;
	  data_out2<=8'b00000000;
	  data_out3<=8'b00000000;
	end
	else begin state <= next_state;
		data_out0<=data_out0_next;
		data_out1<=data_out1_next;	//Flops para mantener el dato y evitar latches
		data_out2<=data_out2_next;
		data_out3<=data_out3_next;
	end
		

// Bloque de asignacion de los estados y sus transiciones.
 always@(*) begin
	next_state = 8'b00000000;
	data_out0_next=data_out0;  //Evita los Latch inferidos
	data_out1_next=data_out1;
	data_out2_next=data_out2;
	data_out3_next=data_out3;
	case (1'b1)

		state[Estado0]: if(valid) begin next_state [LaneA] = 1'b1;
				
					data_out0_next=data;

			      	end else   next_state [Estado0] = 1'b1;

	
		state[LaneA]: if(valid) begin next_state [LaneB] = 1'b1;
				
					data_out1_next=data;
				
			      end else   next_state [LaneA] = 1'b1;
		
		state[LaneB]: if(valid)begin  next_state [LaneC] = 1'b1;

					data_out2_next=data;			

			      end else   next_state [LaneB] = 1'b1;
		
		state[LaneC]: if(valid) begin next_state [LaneD] = 1'b1;

					data_out3_next=data;

			      end else next_state [LaneC] = 1'b1;
      		
		state[LaneD]: if(valid) begin next_state [LaneA] = 1'b1;

				
					data_out0_next = data;			

			      end else next_state [LaneD] = 1'b1;
	endcase
end
endmodule

miscelaneos/Byte_Striping/tbbs.v
//Alejandro Rojas Cordero Tarea 6 B36049
`include "bpbs.v"

module tbbs;

wire clk;

bytestripingRX bytestrip (.clk(clk), .data(data), .reset(reset),.valid(valid),.data_out0(data_out0), .data_out1(data_out1), .data_out2(data_out2), .data_out3(data_out3));
bpbs bancopruebasBS (.clk(clk), .data(data), .reset(reset), .valid(valid),.data_out0(data_out0), .data_out1(data_out1), .data_out2(data_out2), .data_out3(data_out3));

initial begin
    
  //-- Fichero donde almacenar los resultados
  $dumpfile("prueba_Byte_Striping.vcd");
  $dumpvars(0, tbbs);
    
  # 600 $display("FIN TestBench");
  $finish;
end


endmodule

miscelaneos/Byte_Striping/Tx/prueba_Byte_StripingTX.vcd
$date
	Wed May 23 17:17:59 2018
$end
$version
	Icarus Verilog
$end
$timescale
	1s
$end
$scope module tbbs $end
$var wire 1 ! valid $end
$var wire 1 " reset $end
$var wire 8 # data_out3 [7:0] $end
$var wire 8 $ data_out2 [7:0] $end
$var wire 8 % data_out1 [7:0] $end
$var wire 8 & data_out0 [7:0] $end
$var wire 8 ' data [7:0] $end
$var wire 1 ( clk $end
$scope module bancopruebasBS $end
$var wire 8 ) data_out3 [7:0] $end
$var wire 8 * data_out2 [7:0] $end
$var wire 8 + data_out1 [7:0] $end
$var wire 8 , data_out0 [7:0] $end
$var reg 1 ( clk $end
$var reg 8 - data [7:0] $end
$var reg 1 " reset $end
$var reg 1 ! valid $end
$upscope $end
$scope module bytestrip $end
$var wire 1 ( clk $end
$var wire 8 . data [7:0] $end
$var wire 1 " reset $end
$var wire 1 ! valid $end
$var reg 8 / data_out0 [7:0] $end
$var reg 8 0 data_out0_next [7:0] $end
$var reg 8 1 data_out1 [7:0] $end
$var reg 8 2 data_out1_next [7:0] $end
$var reg 8 3 data_out2 [7:0] $end
$var reg 8 4 data_out2_next [7:0] $end
$var reg 8 5 data_out3 [7:0] $end
$var reg 8 6 data_out3_next [7:0] $end
$var reg 8 7 next_state [7:0] $end
$var reg 8 8 state [7:0] $end
$upscope $end
$upscope $end
$enddefinitions $end
#0
$dumpvars
b10 8
b10 7
b0 6
b0 5
b0 4
b0 3
b0 2
b0 1
b0 0
b0 /
b0 .
b0 -
b0 ,
b0 +
b0 *
b0 )
0(
b0 '
b0 &
b0 %
b0 $
b0 #
0"
0!
$end
#5
b10 7
1"
b10 8
1(
#10
0(
#15
b100 7
1!
1(
#20
0(
#25
b1000 7
b100 8
1(
#30
0(
#35
b10000 7
b1000 8
1(
#40
0(
#45
b1 0
b10 7
b1 '
b1 -
b1 .
b10000 8
1(
#50
0(
#55
b10 2
b100 7
b10 '
b10 -
b10 .
b1 &
b1 ,
b1 /
b10 8
1(
#60
0(
#65
b11 4
b1000 7
b11 '
b11 -
b11 .
b10 %
b10 +
b10 1
b100 8
1(
#70
0(
#75
b100 6
b10000 7
b100 '
b100 -
b100 .
b11 $
b11 *
b11 3
b1000 8
1(
#80
0(
#85
b101 0
b10 7
b101 '
b101 -
b101 .
b100 #
b100 )
b100 5
b10000 8
1(
#90
0(
#95
b110 2
b100 7
b110 '
b110 -
b110 .
b101 &
b101 ,
b101 /
b10 8
1(
#100
0(
#105
b111 4
b1000 7
b111 '
b111 -
b111 .
b110 %
b110 +
b110 1
b100 8
1(
#110
0(
#115
b1000 6
b10000 7
b1000 '
b1000 -
b1000 .
b111 $
b111 *
b111 3
b1000 8
1(
#120
0(
#125
b1001 0
b10 7
b1001 '
b1001 -
b1001 .
b1000 #
b1000 )
b1000 5
b10000 8
1(
#130
0(
#135
b10000 2
b100 7
b10000 '
b10000 -
b10000 .
b1001 &
b1001 ,
b1001 /
b10 8
1(
#140
0(
#145
b10001 4
b1000 7
b10001 '
b10001 -
b10001 .
b10000 %
b10000 +
b10000 1
b100 8
1(
#150
0(
#155
b10010 6
b10000 7
b10010 '
b10010 -
b10010 .
b10001 $
b10001 *
b10001 3
b1000 8
1(
#160
0(
#165
b10010 0
b10 7
b10010 #
b10010 )
b10010 5
b10000 8
1(
#170
0(
#175
b10010 2
b100 7
b10010 &
b10010 ,
b10010 /
b10 8
1(
#180
0(
#185
b10010 4
b1000 7
b10010 %
b10010 +
b10010 1
b100 8
1(
#190
0(
#195
b10000 7
b10010 $
b10010 *
b10010 3
b1000 8
1(
#200
0(
#205
b10 7
b10000 8
1(
#210
0(
#215
b100 7
b10 8
1(
#220
0(
#225
b1000 7
b100 8
1(
#230
0(
#235
b10000 7
b1000 8
1(
#240
0(
#245
b10 7
b10000 8
1(
#250
0(
#255
b100 7
b10 8
1(
#260
0(
#265
b1000 7
b100 8
1(
#270
0(
#275
b10000 7
b1000 8
1(
#280
0(
#285
b10 7
b10000 8
1(
#290
0(
#295
b100 7
b10 8
1(
#300
0(
#305
b1000 7
b100 8
1(
#310
0(
#315
b10000 7
b1000 8
1(
#320
0(
#325
b10 7
b10000 8
1(
#330
0(
#335
b100 7
b10 8
1(
#340
0(
#345
b1000 7
b100 8
1(
#350
0(
#355
b10000 7
b1000 8
1(
#360
0(
#365
b10 7
b10000 8
1(
#370
0(
#375
b100 7
b10 8
1(
#380
0(
#385
b1000 7
b100 8
1(
#390
0(
#395
b10000 7
b1000 8
1(
#400
0(
#405
b10 7
b10000 8
1(
#410
0(
#415
b100 7
b10 8
1(
#420
0(
#425
b1000 7
b100 8
1(
#430
0(
#435
b10000 7
b1000 8
1(
#440
0(
#445
b10 7
b10000 8
1(
#450
0(
#455
b100 7
b10 8
1(
#460
0(
#465
b1000 7
b100 8
1(
#470
0(
#475
b10000 7
b1000 8
1(
#480
0(
#485
b10 7
b10000 8
1(
#490
0(
#495
b100 7
b10 8
1(
#500
0(
#505
b1000 7
b100 8
1(
#510
0(
#515
b10000 7
b1000 8
1(
#520
0(
#525
b10 7
b10000 8
1(
#530
0(
#535
b100 7
b10 8
1(
#540
0(
#545
b1000 7
b100 8
1(
#550
0(
#555
b10000 7
b1000 8
1(
#560
0(
#565
b10 7
b10000 8
1(
#570
0(
#575
b100 7
b10 8
1(
#580
0(
#585
b1000 7
b100 8
1(
#590
0(
#595
b10000 7
b1000 8
1(
